[
  {
    "Mes": 1,
    "Ano": 2008,
    "ValorTexto": "1690.4761",
    "Valor": 1690.4761,
    "Variacao": 0.0,
    "VariacaoMensal": 0.0,
    "Amostra": 2
  },
  {
    "Mes": 2,
    "Ano": 2008,
    "ValorTexto": "1690.4761",
    "Valor": 1690.4761,
    "Variacao": 0.0,
    "VariacaoMensal": 0.0,
    "Amostra": 2
  },
  {
    "Mes": 3,
    "Ano": 2008,
    "ValorTexto": "1690.4761",
    "Valor": 1690.4761,
    "Variacao": 0.0,
    "VariacaoMensal": 0.0,
    "Amostra": 2
  },
  {
    "Mes": 4,
    "Ano": 2008,
    "ValorTexto": "1714.2857",
    "Valor": 1714.2857,
    "Variacao": 1.41,
    "VariacaoMensal": 1.41,
    "Amostra": 1
  },
  {
    "Mes": 5,
    "Ano": 2008,
    "ValorTexto": "1714.2857",
    "Valor": 1714.2857,
    "Variacao": 1.41,
    "VariacaoMensal": 0.0,
    "Amostra": 1
  },
  {
    "Mes": 6,
    "Ano": 2008,
    "ValorTexto": "1714.2857",
    "Valor": 1714.2857,
    "Variacao": 1.41,
    "VariacaoMensal": 0.0,
    "Amostra": 1
  },
  {
    "Mes": 7,
    "Ano": 2008,
    "ValorTexto": "1488.2903",
    "Valor": 1488.2903,
    "Variacao": -11.96,
    "VariacaoMensal": -13.18,
    "Amostra": 2
  },
  {
    "Mes": 8,
    "Ano": 2008,
    "ValorTexto": "1758.8602",
    "Valor": 1758.8602,
    "Variacao": 4.05,
    "VariacaoMensal": 18.18,
    "Amostra": 3
  },
  {
    "Mes": 9,
    "Ano": 2008,
    "ValorTexto": "1890.6047",
    "Valor": 1890.6047,
    "Variacao": 11.84,
    "VariacaoMensal": 7.49,
    "Amostra": 32
  },
  {
    "Mes": 10,
    "Ano": 2008,
    "ValorTexto": "1929.4735",
    "Valor": 1929.4735,
    "Variacao": 14.14,
    "VariacaoMensal": 2.06,
    "Amostra": 31
  },
  {
    "Mes": 11,
    "Ano": 2008,
    "ValorTexto": "1885.9249",
    "Valor": 1885.9249,
    "Variacao": 11.56,
    "VariacaoMensal": -2.26,
    "Amostra": 46
  },
  {
    "Mes": 12,
    "Ano": 2008,
    "ValorTexto": "1935.3055",
    "Valor": 1935.3055,
    "Variacao": 14.48,
    "VariacaoMensal": 2.62,
    "Amostra": 40
  },
  {
    "Mes": 1,
    "Ano": 2009,
    "ValorTexto": "1903.3681",
    "Valor": 1903.3681,
    "Variacao": 12.59,
    "VariacaoMensal": -1.65,
    "Amostra": 40
  },
  {
    "Mes": 2,
    "Ano": 2009,
    "ValorTexto": "1878.3982",
    "Valor": 1878.3982,
    "Variacao": 11.12,
    "VariacaoMensal": -1.31,
    "Amostra": 44
  },
  {
    "Mes": 3,
    "Ano": 2009,
    "ValorTexto": "1920.6092",
    "Valor": 1920.6092,
    "Variacao": 13.61,
    "VariacaoMensal": 2.25,
    "Amostra": 44
  },
  {
    "Mes": 4,
    "Ano": 2009,
    "ValorTexto": "1918.3675",
    "Valor": 1918.3675,
    "Variacao": 13.48,
    "VariacaoMensal": -0.12,
    "Amostra": 59
  },
  {
    "Mes": 5,
    "Ano": 2009,
    "ValorTexto": "1912.1831",
    "Valor": 1912.1831,
    "Variacao": 13.12,
    "VariacaoMensal": -0.32,
    "Amostra": 49
  },
  {
    "Mes": 6,
    "Ano": 2009,
    "ValorTexto": "1977.4037",
    "Valor": 1977.4037,
    "Variacao": 16.97,
    "VariacaoMensal": 3.41,
    "Amostra": 46
  },
  {
    "Mes": 7,
    "Ano": 2009,
    "ValorTexto": "2069.1389",
    "Valor": 2069.1389,
    "Variacao": 22.4,
    "VariacaoMensal": 4.64,
    "Amostra": 42
  },
  {
    "Mes": 8,
    "Ano": 2009,
    "ValorTexto": "2082.8392",
    "Valor": 2082.8392,
    "Variacao": 23.21,
    "VariacaoMensal": 0.66,
    "Amostra": 36
  },
  {
    "Mes": 9,
    "Ano": 2009,
    "ValorTexto": "2190.4136",
    "Valor": 2190.4136,
    "Variacao": 29.57,
    "VariacaoMensal": 5.16,
    "Amostra": 32
  },
  {
    "Mes": 10,
    "Ano": 2009,
    "ValorTexto": "2179.5774",
    "Valor": 2179.5774,
    "Variacao": 28.93,
    "VariacaoMensal": -0.49,
    "Amostra": 35
  },
  {
    "Mes": 11,
    "Ano": 2009,
    "ValorTexto": "2181.7777",
    "Valor": 2181.7777,
    "Variacao": 29.06,
    "VariacaoMensal": 0.1,
    "Amostra": 33
  },
  {
    "Mes": 12,
    "Ano": 2009,
    "ValorTexto": "2100.2999",
    "Valor": 2100.2999,
    "Variacao": 24.24,
    "VariacaoMensal": -3.73,
    "Amostra": 36
  },
  {
    "Mes": 1,
    "Ano": 2010,
    "ValorTexto": "2164.7689",
    "Valor": 2164.7689,
    "Variacao": 28.06,
    "VariacaoMensal": 3.07,
    "Amostra": 38
  },
  {
    "Mes": 2,
    "Ano": 2010,
    "ValorTexto": "2192.4751",
    "Valor": 2192.4751,
    "Variacao": 29.7,
    "VariacaoMensal": 1.28,
    "Amostra": 44
  },
  {
    "Mes": 3,
    "Ano": 2010,
    "ValorTexto": "2168.4555",
    "Valor": 2168.4555,
    "Variacao": 28.27,
    "VariacaoMensal": -1.1,
    "Amostra": 41
  },
  {
    "Mes": 4,
    "Ano": 2010,
    "ValorTexto": "2219.4367",
    "Valor": 2219.4367,
    "Variacao": 31.29,
    "VariacaoMensal": 2.35,
    "Amostra": 41
  },
  {
    "Mes": 5,
    "Ano": 2010,
    "ValorTexto": "2491.3195",
    "Valor": 2491.3195,
    "Variacao": 47.37,
    "VariacaoMensal": 12.25,
    "Amostra": 61
  },
  {
    "Mes": 6,
    "Ano": 2010,
    "ValorTexto": "2481.6319",
    "Valor": 2481.6319,
    "Variacao": 46.8,
    "VariacaoMensal": -0.39,
    "Amostra": 61
  },
  {
    "Mes": 7,
    "Ano": 2010,
    "ValorTexto": "2490.0211",
    "Valor": 2490.0211,
    "Variacao": 47.3,
    "VariacaoMensal": 0.34,
    "Amostra": 62
  },
  {
    "Mes": 8,
    "Ano": 2010,
    "ValorTexto": "2547.7195",
    "Valor": 2547.7195,
    "Variacao": 50.71,
    "VariacaoMensal": 2.32,
    "Amostra": 54
  },
  {
    "Mes": 9,
    "Ano": 2010,
    "ValorTexto": "2415.8812",
    "Valor": 2415.8812,
    "Variacao": 42.91,
    "VariacaoMensal": -5.17,
    "Amostra": 44
  },
  {
    "Mes": 10,
    "Ano": 2010,
    "ValorTexto": "2410.2227",
    "Valor": 2410.2227,
    "Variacao": 42.58,
    "VariacaoMensal": -0.23,
    "Amostra": 50
  },
  {
    "Mes": 11,
    "Ano": 2010,
    "ValorTexto": "2812.5056",
    "Valor": 2812.5056,
    "Variacao": 66.37,
    "VariacaoMensal": 16.69,
    "Amostra": 39
  },
  {
    "Mes": 12,
    "Ano": 2010,
    "ValorTexto": "2719.2101",
    "Valor": 2719.2101,
    "Variacao": 60.85,
    "VariacaoMensal": -3.32,
    "Amostra": 40
  },
  {
    "Mes": 1,
    "Ano": 2011,
    "ValorTexto": "2838.5261",
    "Valor": 2838.5261,
    "Variacao": 67.91,
    "VariacaoMensal": 4.39,
    "Amostra": 56
  },
  {
    "Mes": 2,
    "Ano": 2011,
    "ValorTexto": "2934.0232",
    "Valor": 2934.0232,
    "Variacao": 73.56,
    "VariacaoMensal": 3.36,
    "Amostra": 59
  },
  {
    "Mes": 3,
    "Ano": 2011,
    "ValorTexto": "2970.2459",
    "Valor": 2970.2459,
    "Variacao": 75.7,
    "VariacaoMensal": 1.23,
    "Amostra": 57
  },
  {
    "Mes": 4,
    "Ano": 2011,
    "ValorTexto": "3020.9364",
    "Valor": 3020.9364,
    "Variacao": 78.7,
    "VariacaoMensal": 1.71,
    "Amostra": 66
  },
  {
    "Mes": 5,
    "Ano": 2011,
    "ValorTexto": "2991.5215",
    "Valor": 2991.5215,
    "Variacao": 76.96,
    "VariacaoMensal": -0.97,
    "Amostra": 68
  },
  {
    "Mes": 6,
    "Ano": 2011,
    "ValorTexto": "3017.6944",
    "Valor": 3017.6944,
    "Variacao": 78.51,
    "VariacaoMensal": 0.87,
    "Amostra": 67
  },
  {
    "Mes": 7,
    "Ano": 2011,
    "ValorTexto": "3103.8261",
    "Valor": 3103.8261,
    "Variacao": 83.61,
    "VariacaoMensal": 2.85,
    "Amostra": 59
  },
  {
    "Mes": 8,
    "Ano": 2011,
    "ValorTexto": "3237.2886",
    "Valor": 3237.2886,
    "Variacao": 91.5,
    "VariacaoMensal": 4.3,
    "Amostra": 68
  },
  {
    "Mes": 9,
    "Ano": 2011,
    "ValorTexto": "3214.3063",
    "Valor": 3214.3063,
    "Variacao": 90.14,
    "VariacaoMensal": -0.71,
    "Amostra": 58
  },
  {
    "Mes": 10,
    "Ano": 2011,
    "ValorTexto": "3232.9803",
    "Valor": 3232.9803,
    "Variacao": 91.25,
    "VariacaoMensal": 0.58,
    "Amostra": 62
  },
  {
    "Mes": 11,
    "Ano": 2011,
    "ValorTexto": "3302.8421",
    "Valor": 3302.8421,
    "Variacao": 95.38,
    "VariacaoMensal": 2.16,
    "Amostra": 68
  },
  {
    "Mes": 12,
    "Ano": 2011,
    "ValorTexto": "3429.0237",
    "Valor": 3429.0237,
    "Variacao": 102.84,
    "VariacaoMensal": 3.82,
    "Amostra": 64
  },
  {
    "Mes": 1,
    "Ano": 2012,
    "ValorTexto": "3452.2048",
    "Valor": 3452.2048,
    "Variacao": 104.21,
    "VariacaoMensal": 0.68,
    "Amostra": 80
  },
  {
    "Mes": 2,
    "Ano": 2012,
    "ValorTexto": "3526.164",
    "Valor": 3526.164,
    "Variacao": 108.59,
    "VariacaoMensal": 2.14,
    "Amostra": 66
  },
  {
    "Mes": 3,
    "Ano": 2012,
    "ValorTexto": "3485.0865",
    "Valor": 3485.0865,
    "Variacao": 106.16,
    "VariacaoMensal": -1.16,
    "Amostra": 62
  },
  {
    "Mes": 4,
    "Ano": 2012,
    "ValorTexto": "3535.0727",
    "Valor": 3535.0727,
    "Variacao": 109.12,
    "VariacaoMensal": 1.43,
    "Amostra": 58
  },
  {
    "Mes": 5,
    "Ano": 2012,
    "ValorTexto": "3464.425",
    "Valor": 3464.425,
    "Variacao": 104.94,
    "VariacaoMensal": -2.0,
    "Amostra": 55
  },
  {
    "Mes": 6,
    "Ano": 2012,
    "ValorTexto": "3626.1088",
    "Valor": 3626.1088,
    "Variacao": 114.5,
    "VariacaoMensal": 4.67,
    "Amostra": 43
  },
  {
    "Mes": 7,
    "Ano": 2012,
    "ValorTexto": "3619.6325",
    "Valor": 3619.6325,
    "Variacao": 114.12,
    "VariacaoMensal": -0.18,
    "Amostra": 54
  },
  {
    "Mes": 8,
    "Ano": 2012,
    "ValorTexto": "3715.2378",
    "Valor": 3715.2378,
    "Variacao": 119.77,
    "VariacaoMensal": 2.64,
    "Amostra": 74
  },
  {
    "Mes": 9,
    "Ano": 2012,
    "ValorTexto": "3801.3632",
    "Valor": 3801.3632,
    "Variacao": 124.87,
    "VariacaoMensal": 2.32,
    "Amostra": 73
  },
  {
    "Mes": 10,
    "Ano": 2012,
    "ValorTexto": "3932.0006",
    "Valor": 3932.0006,
    "Variacao": 132.6,
    "VariacaoMensal": 3.44,
    "Amostra": 64
  },
  {
    "Mes": 11,
    "Ano": 2012,
    "ValorTexto": "4040.7279",
    "Valor": 4040.7279,
    "Variacao": 139.03,
    "VariacaoMensal": 2.77,
    "Amostra": 67
  },
  {
    "Mes": 12,
    "Ano": 2012,
    "ValorTexto": "4115.2036",
    "Valor": 4115.2036,
    "Variacao": 143.43,
    "VariacaoMensal": 1.84,
    "Amostra": 57
  },
  {
    "Mes": 1,
    "Ano": 2013,
    "ValorTexto": "4135.0417",
    "Valor": 4135.0417,
    "Variacao": 144.61,
    "VariacaoMensal": 0.48,
    "Amostra": 53
  },
  {
    "Mes": 2,
    "Ano": 2013,
    "ValorTexto": "4189.163",
    "Valor": 4189.163,
    "Variacao": 147.81,
    "VariacaoMensal": 1.31,
    "Amostra": 55
  },
  {
    "Mes": 3,
    "Ano": 2013,
    "ValorTexto": "4345.5862",
    "Valor": 4345.5862,
    "Variacao": 157.06,
    "VariacaoMensal": 3.73,
    "Amostra": 69
  },
  {
    "Mes": 4,
    "Ano": 2013,
    "ValorTexto": "4445.7667",
    "Valor": 4445.7667,
    "Variacao": 162.99,
    "VariacaoMensal": 2.31,
    "Amostra": 80
  },
  {
    "Mes": 5,
    "Ano": 2013,
    "ValorTexto": "4471.0702",
    "Valor": 4471.0702,
    "Variacao": 164.49,
    "VariacaoMensal": 0.57,
    "Amostra": 74
  },
  {
    "Mes": 6,
    "Ano": 2013,
    "ValorTexto": "4455.4675",
    "Valor": 4455.4675,
    "Variacao": 163.56,
    "VariacaoMensal": -0.35,
    "Amostra": 72
  },
  {
    "Mes": 7,
    "Ano": 2013,
    "ValorTexto": "4571.1259",
    "Valor": 4571.1259,
    "Variacao": 170.4,
    "VariacaoMensal": 2.6,
    "Amostra": 57
  },
  {
    "Mes": 8,
    "Ano": 2013,
    "ValorTexto": "4520.5173",
    "Valor": 4520.5173,
    "Variacao": 167.41,
    "VariacaoMensal": -1.11,
    "Amostra": 59
  },
  {
    "Mes": 9,
    "Ano": 2013,
    "ValorTexto": "4855.26",
    "Valor": 4855.26,
    "Variacao": 187.21,
    "VariacaoMensal": 7.4,
    "Amostra": 72
  },
  {
    "Mes": 10,
    "Ano": 2013,
    "ValorTexto": "4859.0832",
    "Valor": 4859.0832,
    "Variacao": 187.44,
    "VariacaoMensal": 0.08,
    "Amostra": 77
  },
  {
    "Mes": 11,
    "Ano": 2013,
    "ValorTexto": "4769.9883",
    "Valor": 4769.9883,
    "Variacao": 182.17,
    "VariacaoMensal": -1.83,
    "Amostra": 53
  },
  {
    "Mes": 12,
    "Ano": 2013,
    "ValorTexto": "4712.3871",
    "Valor": 4712.3871,
    "Variacao": 178.76,
    "VariacaoMensal": -1.21,
    "Amostra": 59
  },
  {
    "Mes": 1,
    "Ano": 2014,
    "ValorTexto": "4885.3005",
    "Valor": 4885.3005,
    "Variacao": 188.99,
    "VariacaoMensal": 3.67,
    "Amostra": 71
  },
  {
    "Mes": 2,
    "Ano": 2014,
    "ValorTexto": "4725.1911",
    "Valor": 4725.1911,
    "Variacao": 179.52,
    "VariacaoMensal": -3.28,
    "Amostra": 80
  }
]